socketshelp/3x3x3.py
socketshelp/__init__.py
socketshelp/bar.py
socketshelp/barh.py
socketshelp/csv.py
socketshelp/csvbar.py
socketshelp/download.py
socketshelp/equal.py
socketshelp/frequent.py
socketshelp/hindi.py
socketshelp/icmp.py
socketshelp/label.py
socketshelp/largest.py
socketshelp/max.py
socketshelp/normal.py
socketshelp/profile.py
socketshelp/sort.py
socketshelp/students.py
socketshelp/tcp.py
socketshelp/udp.py
socketshelp-0.0.1.dist-info/LICENSE
socketshelp-0.0.1.dist-info/METADATA
socketshelp-0.0.1.dist-info/WHEEL
socketshelp-0.0.1.dist-info/top_level.txt
socketshelp-0.0.1.dist-info/RECORD
